[{"line":1,"elements":[{"line":4,"name":"","description":"","type":"background","keyword":"Background","steps":[{"name":"url 'https:\/\/simple-grocery-store-api.glitch.me'","result":{"duration":204600,"status":"passed"},"match":{"location":"karate","arguments":[]},"keyword":"Given","line":5,"doc_string":{"content_type":"","value":"10:09:43.283 karate.env system property was: null \n","line":5}}]},{"start_timestamp":"2024-05-16T04:39:43.282Z","line":7,"name":"To get the list of all products from grocery api","description":"","id":"to-get-the-list-of-all-products-from-grocery-api","type":"scenario","keyword":"Scenario","steps":[{"name":"path '\/products'","result":{"duration":589300,"status":"passed"},"match":{"location":"karate","arguments":[]},"keyword":"Given","line":8},{"name":"header Accept = 'application\/json'","result":{"duration":188400,"status":"passed"},"match":{"location":"karate","arguments":[]},"keyword":"And","line":9},{"name":"method get","result":{"duration":839825000,"status":"passed"},"match":{"location":"karate","arguments":[]},"keyword":"When","line":10,"doc_string":{"content_type":"","value":"10:09:43.289 request:\n1 > GET https:\/\/simple-grocery-store-api.glitch.me\/products\n1 > Accept: application\/json\n1 > Host: simple-grocery-store-api.glitch.me\n1 > Connection: Keep-Alive\n1 > User-Agent: Apache-HttpClient\/4.5.14 (Java\/11.0.22)\n1 > Accept-Encoding: gzip,deflate\n\n\n10:09:44.121 response time in milliseconds: 831\n1 < 200\n1 < Date: Thu, 16 May 2024 04:39:43 GMT\n1 < Content-Type: application\/json; charset=utf-8\n1 < Content-Length: 1716\n1 < Connection: keep-alive\n1 < x-powered-by: Express\n1 < etag: W\/\"6b4-RVZTrjCoC03tQFslV\/oF2zXZ8Wo\"\n[{\"id\":4643,\"category\":\"coffee\",\"name\":\"Starbucks Coffee Variety Pack, 100% Arabica\",\"inStock\":true},{\"id\":4646,\"category\":\"coffee\",\"name\":\"Ethical Bean Medium Dark Roast, Espresso\",\"inStock\":true},{\"id\":4641,\"category\":\"coffee\",\"name\":\"Don Francisco Colombia Supremo Medium Roast\",\"inStock\":true},{\"id\":1225,\"category\":\"fresh-produce\",\"name\":\"1\/2 in. Brushless Hammer Drill\",\"inStock\":true},{\"id\":3674,\"category\":\"fresh-produce\",\"name\":\"20V Max Cordless Drill Combo Kit\",\"inStock\":true},{\"id\":2585,\"category\":\"fresh-produce\",\"name\":\"Green Cabbage Organic\",\"inStock\":true},{\"id\":5851,\"category\":\"fresh-produce\",\"name\":\"Cucumber Organic\",\"inStock\":false},{\"id\":8739,\"category\":\"fresh-produce\",\"name\":\"Fresh Spinach Organic\",\"inStock\":true},{\"id\":2177,\"category\":\"meat-seafood\",\"name\":\"Cosco Three Step Steel Platform\",\"inStock\":true},{\"id\":1709,\"category\":\"meat-seafood\",\"name\":\"Beef Choice Angus Ribeye Steak\",\"inStock\":true},{\"id\":1709,\"category\":\"meat-seafood\",\"name\":\"Angus Steak Burgers\",\"inStock\":true},{\"id\":7395,\"category\":\"meat-seafood\",\"name\":\"Boneless Skinless Chicken Breasts\",\"inStock\":true},{\"id\":8554,\"category\":\"candy\",\"name\":\"Kinder Joy Eggs\",\"inStock\":true},{\"id\":6483,\"category\":\"candy\",\"name\":\"Cadbury Milk Chocolate\",\"inStock\":true},{\"id\":5774,\"category\":\"candy\",\"name\":\"HERSHEY'S, Milk Chocolate Almond\",\"inStock\":true},{\"id\":8753,\"category\":\"dairy\",\"name\":\"Reduced Fat Milk\",\"inStock\":true},{\"id\":9482,\"category\":\"dairy\",\"name\":\"Whole Milk\",\"inStock\":true},{\"id\":5477,\"category\":\"dairy\",\"name\":\"Cream Cheese\",\"inStock\":true},{\"id\":5478,\"category\":\"dairy\",\"name\":\"Low Fat Vanilla Yogurt\",\"inStock\":true},{\"id\":4875,\"category\":\"bread-bakery\",\"name\":\"2800 Watt Inverter Generator\",\"inStock\":true}]\n\n","line":10}},{"name":"status 200","result":{"duration":9000,"status":"passed"},"match":{"location":"karate","arguments":[]},"keyword":"Then","line":11},{"name":"print response","result":{"duration":1315700,"status":"passed"},"match":{"location":"karate","arguments":[]},"keyword":"And","line":12,"doc_string":{"content_type":"","value":"10:09:44.126 [print] [\n  {\n    \"id\": 4643,\n    \"category\": \"coffee\",\n    \"name\": \"Starbucks Coffee Variety Pack, 100% Arabica\",\n    \"inStock\": true\n  },\n  {\n    \"id\": 4646,\n    \"category\": \"coffee\",\n    \"name\": \"Ethical Bean Medium Dark Roast, Espresso\",\n    \"inStock\": true\n  },\n  {\n    \"id\": 4641,\n    \"category\": \"coffee\",\n    \"name\": \"Don Francisco Colombia Supremo Medium Roast\",\n    \"inStock\": true\n  },\n  {\n    \"id\": 1225,\n    \"category\": \"fresh-produce\",\n    \"name\": \"1\/2 in. Brushless Hammer Drill\",\n    \"inStock\": true\n  },\n  {\n    \"id\": 3674,\n    \"category\": \"fresh-produce\",\n    \"name\": \"20V Max Cordless Drill Combo Kit\",\n    \"inStock\": true\n  },\n  {\n    \"id\": 2585,\n    \"category\": \"fresh-produce\",\n    \"name\": \"Green Cabbage Organic\",\n    \"inStock\": true\n  },\n  {\n    \"id\": 5851,\n    \"category\": \"fresh-produce\",\n    \"name\": \"Cucumber Organic\",\n    \"inStock\": false\n  },\n  {\n    \"id\": 8739,\n    \"category\": \"fresh-produce\",\n    \"name\": \"Fresh Spinach Organic\",\n    \"inStock\": true\n  },\n  {\n    \"id\": 2177,\n    \"category\": \"meat-seafood\",\n    \"name\": \"Cosco Three Step Steel Platform\",\n    \"inStock\": true\n  },\n  {\n    \"id\": 1709,\n    \"category\": \"meat-seafood\",\n    \"name\": \"Beef Choice Angus Ribeye Steak\",\n    \"inStock\": true\n  },\n  {\n    \"id\": 1709,\n    \"category\": \"meat-seafood\",\n    \"name\": \"Angus Steak Burgers\",\n    \"inStock\": true\n  },\n  {\n    \"id\": 7395,\n    \"category\": \"meat-seafood\",\n    \"name\": \"Boneless Skinless Chicken Breasts\",\n    \"inStock\": true\n  },\n  {\n    \"id\": 8554,\n    \"category\": \"candy\",\n    \"name\": \"Kinder Joy Eggs\",\n    \"inStock\": true\n  },\n  {\n    \"id\": 6483,\n    \"category\": \"candy\",\n    \"name\": \"Cadbury Milk Chocolate\",\n    \"inStock\": true\n  },\n  {\n    \"id\": 5774,\n    \"category\": \"candy\",\n    \"name\": \"HERSHEY'S, Milk Chocolate Almond\",\n    \"inStock\": true\n  },\n  {\n    \"id\": 8753,\n    \"category\": \"dairy\",\n    \"name\": \"Reduced Fat Milk\",\n    \"inStock\": true\n  },\n  {\n    \"id\": 9482,\n    \"category\": \"dairy\",\n    \"name\": \"Whole Milk\",\n    \"inStock\": true\n  },\n  {\n    \"id\": 5477,\n    \"category\": \"dairy\",\n    \"name\": \"Cream Cheese\",\n    \"inStock\": true\n  },\n  {\n    \"id\": 5478,\n    \"category\": \"dairy\",\n    \"name\": \"Low Fat Vanilla Yogurt\",\n    \"inStock\": true\n  },\n  {\n    \"id\": 4875,\n    \"category\": \"bread-bakery\",\n    \"name\": \"2800 Watt Inverter Generator\",\n    \"inStock\": true\n  }\n]\n \n","line":12}}],"tags":[]}],"name":"com\/api\/automation\/products\/getAllProducts.feature","description":"To test the products endpoint of grocery api\nThis get the list of products from inventory","id":"to-test-the-products-endpoint-of-grocery-api","keyword":"Feature","uri":"com\/api\/automation\/products\/getAllProducts.feature"}]